{
    "n_review": 6685900,
    "n_review_2018": 1177662,
    "n_user": 1637138,
    "top10_user": [
        [
            "CxDOIDnH8gp9KXzpBHJYXw",
            4129
        ],
        [
            "bLbSNkLggFnqwNNzzq-Ijw",
            2354
        ],
        [
            "PKEzKWv_FktMm2mGPjwd0Q",
            1822
        ],
        [
            "ELcQDlf69kb-ihJfxZyL0A",
            1764
        ],
        [
            "DK57YibC5ShBmqQl97CKog",
            1727
        ],
        [
            "U4INQZOPSUaj8hMjLlZ3KA",
            1559
        ],
        [
            "QJI9OSEn6ujRCtrX06vs1w",
            1496
        ],
        [
            "d_TBs6J3twMy9GChqUEXkg",
            1360
        ],
        [
            "hWDybu_KvYLSdEFzGrniTw",
            1355
        ],
        [
            "cMEtAiW60I5wE_vLfTxoJQ",
            1255
        ]
    ],
    "n_business": 192606,
    "top10_business": [
        [
            "4JNXUYY8wbaaDmk3BPzlWw",
            8570
        ],
        [
            "RESDUcs7fIiihp38-d6_6g",
            8568
        ],
        [
            "K7lWdNUhCbcnEvI0NhGewg",
            6887
        ],
        [
            "f4x1YBxkLrZg652xt2KR5g",
            5847
        ],
        [
            "cYwJA2A6I12KNkm2rtXd5g",
            5575
        ],
        [
            "DkYS3arLOhA8si5uUEmHOw",
            5206
        ],
        [
            "2weQS-RnoOBhb1KsHKyoSQ",
            4534
        ],
        [
            "5LNZ67Yw9RD6nf4_UhXOjw",
            4522
        ],
        [
            "iCQpiavjjPzJ5_3gPD5Ebg",
            4351
        ],
        [
            "SMPbvZLSMMb7KU76YNYMGg",
            4350
        ]
    ]
}